{"config": {"view": {"continuousWidth": 300, "continuousHeight": 300}}, "data": {"name": "data-8b69e27aab1d1f7a8d927183b024447e"}, "mark": {"type": "bar"}, "encoding": {"color": {"field": "total_gross", "legend": null, "scale": {"scheme": "blues"}, "type": "quantitative"}, "tooltip": [{"field": "movie_title", "type": "nominal"}, {"field": "genre", "type": "nominal"}, {"field": "release_date", "type": "temporal"}, {"field": "total_gross", "type": "quantitative"}], "x": {"axis": {"format": "$.2s"}, "field": "total_gross", "title": "Total Gross (USD)", "type": "quantitative"}, "y": {"field": "movie_title", "sort": "-x", "title": null, "type": "nominal"}}, "height": 700, "title": "Top 25 Hits of the Disney Renaissance (1989-1999)", "width": 1000, "$schema": "https://vega.github.io/schema/vega-lite/v5.20.1.json", "datasets": {"data-8b69e27aab1d1f7a8d927183b024447e": [{"movie_title": "The Lion King", "release_date": "1994-06-15T00:00:00", "genre": "Adventure", "MPAA_rating": "G", "total_gross": 422780140.0, "inflation_adjusted_gross": "$761,640,898"}, {"movie_title": "The Sixth Sense", "release_date": "1999-08-06T00:00:00", "genre": "Thriller/Suspense", "MPAA_rating": "PG-13", "total_gross": 293506292.0, "inflation_adjusted_gross": "$485,424,724"}, {"movie_title": "Toy Story 2", "release_date": "1999-11-19T00:00:00", "genre": "Adventure", "MPAA_rating": "G", "total_gross": 245852179.0, "inflation_adjusted_gross": "$404,450,426"}, {"movie_title": "Beauty and the Beast", "release_date": "1991-11-13T00:00:00", "genre": "Musical", "MPAA_rating": "G", "total_gross": 218951625.0, "inflation_adjusted_gross": "$363,017,667"}, {"movie_title": "Aladdin", "release_date": "1992-11-11T00:00:00", "genre": "Comedy", "MPAA_rating": "G", "total_gross": 217350219.0, "inflation_adjusted_gross": "$441,969,178"}, {"movie_title": "Armageddon", "release_date": "1998-07-01T00:00:00", "genre": "Adventure", "MPAA_rating": "PG-13", "total_gross": 201578182.0, "inflation_adjusted_gross": "$362,324,957"}, {"movie_title": "Toy Story", "release_date": "1995-11-22T00:00:00", "genre": "Adventure", "MPAA_rating": "G", "total_gross": 191796233.0, "inflation_adjusted_gross": "$370,409,631"}, {"movie_title": "Pretty Woman", "release_date": "1990-03-23T00:00:00", "genre": "Romantic Comedy", "MPAA_rating": "R", "total_gross": 178406268.0, "inflation_adjusted_gross": "$356,389,765"}, {"movie_title": "Tarzan", "release_date": "1999-06-16T00:00:00", "genre": "Adventure", "MPAA_rating": "G", "total_gross": 171091819.0, "inflation_adjusted_gross": "$283,900,254"}, {"movie_title": "A Bug's Life", "release_date": "1998-11-20T00:00:00", "genre": "Adventure", "MPAA_rating": "G", "total_gross": 162798565.0, "inflation_adjusted_gross": "$288,981,698"}, {"movie_title": "The Waterboy", "release_date": "1998-11-06T00:00:00", "genre": "Comedy", "MPAA_rating": "PG-13", "total_gross": 161491646.0, "inflation_adjusted_gross": "$288,691,833"}, {"movie_title": "The Santa Clause", "release_date": "1994-11-11T00:00:00", "genre": "Comedy", "MPAA_rating": "PG", "total_gross": 144833357.0, "inflation_adjusted_gross": "$298,369,717"}, {"movie_title": "Pocahontas", "release_date": "1995-06-10T00:00:00", "genre": "Adventure", "MPAA_rating": "G", "total_gross": 141579773.0, "inflation_adjusted_gross": "$274,370,957"}, {"movie_title": "Sister Act", "release_date": "1992-05-29T00:00:00", "genre": "Comedy", "MPAA_rating": "PG", "total_gross": 139605150.0, "inflation_adjusted_gross": "$283,583,472"}, {"movie_title": "Ransom", "release_date": "1996-11-08T00:00:00", "genre": "Action", "MPAA_rating": "R", "total_gross": 136492681.0, "inflation_adjusted_gross": "$259,807,820"}, {"movie_title": "101 Dalmatians", "release_date": "1996-11-27T00:00:00", "genre": "Comedy", "MPAA_rating": "G", "total_gross": 136189294.0, "inflation_adjusted_gross": "$258,728,898"}, {"movie_title": "The Rock", "release_date": "1996-06-07T00:00:00", "genre": "Action", "MPAA_rating": "R", "total_gross": 134069511.0, "inflation_adjusted_gross": "$255,702,705"}, {"movie_title": "Honey, I Shrunk the Kids", "release_date": "1989-06-23T00:00:00", "genre": "Adventure", "MPAA_rating": "PG", "total_gross": 130724172.0, "inflation_adjusted_gross": "$276,191,669"}, {"movie_title": "Mulan", "release_date": "1998-06-19T00:00:00", "genre": "Adventure", "MPAA_rating": "G", "total_gross": 120620254.0, "inflation_adjusted_gross": "$216,807,832"}, {"movie_title": "Enemy of the State", "release_date": "1998-11-20T00:00:00", "genre": "Action", "MPAA_rating": "R", "total_gross": 111549836.0, "inflation_adjusted_gross": "$198,472,008"}, {"movie_title": "The Little Mermaid", "release_date": "1989-11-15T00:00:00", "genre": "Adventure", "MPAA_rating": "G", "total_gross": 111543479.0, "inflation_adjusted_gross": "$223,726,012"}, {"movie_title": "George Of The Jungle", "release_date": "1997-07-16T00:00:00", "genre": "Comedy", "MPAA_rating": "PG", "total_gross": 105263257.0, "inflation_adjusted_gross": "$193,326,632"}, {"movie_title": "Phenomenon", "release_date": "1996-07-05T00:00:00", "genre": "Drama", "MPAA_rating": "PG", "total_gross": 104636382.0, "inflation_adjusted_gross": "$199,559,799"}, {"movie_title": "Dick Tracy", "release_date": "1990-06-15T00:00:00", "genre": "Action", "MPAA_rating": "PG", "total_gross": 103738726.0, "inflation_adjusted_gross": "$207,231,621"}, {"movie_title": "Con Air", "release_date": "1997-06-06T00:00:00", "genre": "Action", "MPAA_rating": "R", "total_gross": 101117573.0, "inflation_adjusted_gross": "$185,712,664"}, {"movie_title": "The Hunchback of Notre Dame", "release_date": "1996-06-21T00:00:00", "genre": "Adventure", "MPAA_rating": "G", "total_gross": 100138851.0, "inflation_adjusted_gross": "$190,988,799"}, {"movie_title": "Hercules", "release_date": "1997-06-13T00:00:00", "genre": "Adventure", "MPAA_rating": "G", "total_gross": 99112101.0, "inflation_adjusted_gross": "$182,029,412"}, {"movie_title": "Inspector Gadget", "release_date": "1999-07-23T00:00:00", "genre": "Comedy", "MPAA_rating": "PG", "total_gross": 97387965.0, "inflation_adjusted_gross": "$161,610,341"}, {"movie_title": "Dead Poets Society", "release_date": "1989-06-02T00:00:00", "genre": "Drama", "MPAA_rating": "PG", "total_gross": 95860116.0, "inflation_adjusted_gross": "$202,531,517"}, {"movie_title": "Flubber", "release_date": "1997-11-26T00:00:00", "genre": "Comedy", "MPAA_rating": "PG", "total_gross": 92993801.0, "inflation_adjusted_gross": "$170,406,423"}]}}